cmdsave/cmdsave.py
cmdsave-1.0.3.dist-info/METADATA
cmdsave-1.0.3.dist-info/WHEEL
cmdsave-1.0.3.dist-info/entry_points.txt
cmdsave-1.0.3.dist-info/top_level.txt
cmdsave-1.0.3.dist-info/RECORD
