Metadata-Version: 2.1
Name: cmdsave
Version: 1.0.3
Summary: 💾 CMDs
Keywords: save,cli,console,terminal,prductivity
Platform: Windows
Classifier: Programming Language :: Python :: 3.10
Classifier: Operating System :: Microsoft :: Windows
Requires-Dist: argparse
Requires-Dist: tabulate
Requires-Dist: keyboard
Requires-Dist: pyperclip
